LICENSE
MANIFEST.in
README.md
setup.cfg
setup.py
ariblib/__init__.py
ariblib/__main__.py
ariblib/aribgaiji.py
ariblib/aribstr.py
ariblib/caption.py
ariblib/constants.py
ariblib/descriptors.py
ariblib/drcs.py
ariblib/drcs.tsv
ariblib/event.py
ariblib/mnemonics.py
ariblib/packet.py
ariblib/sections.py
ariblib/service.py
ariblib/syntax.py
ariblib/tables.py
ariblib.egg-info/PKG-INFO
ariblib.egg-info/SOURCES.txt
ariblib.egg-info/dependency_links.txt
ariblib.egg-info/pbr.json
ariblib.egg-info/top_level.txt
ariblib/command/__init__.py
ariblib/command/split.py
ariblib/command/vnum.py
ariblib/command/vtt.py