Metadata-Version: 1.1
Name: ariblib
Version: 0.0.5
Summary: python implementation of arib-std-b10 and arib-std-b24
Home-page: http://github.com/youzaka/ariblib
Author: Chisa Youzaka
Author-email: ariblib@txqz.net
License: MIT
Platform: UNKNOWN
Classifier: Programming Language :: Python :: 3
Classifier: License :: OSI Approved :: MIT License
Classifier: Intended Audience :: Developers
Classifier: Development Status :: 3 - Alpha
Classifier: Natural Language :: Japanese
